LICENSE
MANIFEST.in
README.md
setup.py
pyramid_settings/__init__.py
pyramid_settings.egg-info/PKG-INFO
pyramid_settings.egg-info/SOURCES.txt
pyramid_settings.egg-info/dependency_links.txt
pyramid_settings.egg-info/not-zip-safe
pyramid_settings.egg-info/top_level.txt
tests/__init__.py
tests/test_import.py
tests/test_parsing.py