Metadata-Version: 1.1
Name: pyramid-settings
Version: 0.1.2
Summary: Pyramid settings module that lets you use settings.py
Home-page: http://github.com/niktto/pyramid_settings/
Author: Marek Szwalkiewicz
Author-email: marek@szwalkiewicz.waw.pl
License: Copyright (c) 2013, Marek Szwałkiewicz
